<?xml version="1.0" encoding="utf-8"?>
<ModMetaData>
	<name>Leeani Playable Race</name>
	<packageId>MikeRobe.LeeaniPlayableRace</packageId>
	<author>MikeRobe</author>
	<url>https://github.com/quicksilverfox/RimworldMods/releases/latest</url>
	<supportedVersions>
		<li>1.5</li>
		<li>1.6</li>
	</supportedVersions>
	<modDependencies>
		<li>
			<packageId>ludeon.rimworld.biotech</packageId>
			<displayName>Biotech</displayName>
		</li>
	</modDependencies>
	<description>A nice happy race of people-foxes. Now uses Biotech xenotypes instead of Humanoid Alien Races! Built-in support for EPOE.

	Adds Faction, starting Scenario, playable Xenotype, and some signature stuff.

	Plenty of backstories, as well as names. Suggestions? Find @MikeRobe on the Rimworld Discord.

	Note: This version requires the Biotech DLC and is incompatible with the old Humanoid Alien Races versions.

	</description>
</ModMetaData>